neo3/__init__.py
neo3/blockchain.py
neo3_python-0.1.1.dist-info/LICENSE.md
neo3_python-0.1.1.dist-info/METADATA
neo3_python-0.1.1.dist-info/WHEEL
neo3_python-0.1.1.dist-info/entry_points.txt
neo3_python-0.1.1.dist-info/top_level.txt
neo3_python-0.1.1.dist-info/RECORD
