Metadata-Version: 2.1
Name: neo3-python
Version: 0.1.1
Summary: Python SDK for the NEO 3 blockchain
Home-page: https://github.com/CityOfZion/neo3-python
Author: Erik van den Brink
Author-email: erik@coz.io
Maintainer: Erik van den Brink
Maintainer-email: erik@coz.io
License: MIT license
Keywords: neo3,python,SDK
Platform: UNKNOWN
Classifier: Development Status :: 4 - Beta
Classifier: Intended Audience :: Developers
Classifier: License :: OSI Approved :: MIT License
Classifier: Natural Language :: English
Classifier: Programming Language :: Python :: 3
Classifier: Programming Language :: Python :: 3.7
Requires-Python: >=3.7
Requires-Dist: aiodns (==2.0.0)
Requires-Dist: asynctest (==0.13.0)
Requires-Dist: base58 (==1.0.3)
Requires-Dist: bitarray (==1.0.1)
Requires-Dist: coverage (==5.0.2)
Requires-Dist: Events (==0.3)
Requires-Dist: lz4 (==2.2.1)
Requires-Dist: mmh3 (==2.5.1)
Requires-Dist: mpmath (==1.1.0)
Requires-Dist: mypy (==0.761)
Requires-Dist: mypy-extensions (==0.4.3)
Requires-Dist: netaddr (==0.7.19)
Requires-Dist: Sphinx (==2.2.0)
Requires-Dist: sphinx-autodoc-typehints (==1.7.0)
Requires-Dist: pycodestyle (==2.5.0)
